igloo/__init__.py
igloo/main.py
igloo/mutations.py
igloo/query.py
igloo/subscriptions.py
igloo/utils.py
igloo/models/__init__.py
igloo/models/access_token.py
igloo/models/boolean_variable.py
igloo/models/category_series_node.py
igloo/models/category_series_variable.py
igloo/models/collection.py
igloo/models/environment.py
igloo/models/file_variable.py
igloo/models/float_series_node.py
igloo/models/float_series_variable.py
igloo/models/float_variable.py
igloo/models/notification.py
igloo/models/pending_share.py
igloo/models/pending_transfer.py
igloo/models/string_variable.py
igloo/models/thing.py
igloo/models/user.py
igloo/models/utils.py
igloo/models/variable.py
igloo_python-1.0.18.dist-info/LICENSE.txt
igloo_python-1.0.18.dist-info/METADATA
igloo_python-1.0.18.dist-info/WHEEL
igloo_python-1.0.18.dist-info/top_level.txt
igloo_python-1.0.18.dist-info/RECORD
